parsely/__init__.py
parsely/example.secret.py
parsely/models.py
parsely/parsely.py
parsely/recommendations.py
parsely/tests.py
parsely/utils.py
python_parsely-1.5.0.dist-info/METADATA
python_parsely-1.5.0.dist-info/WHEEL
python_parsely-1.5.0.dist-info/top_level.txt
python_parsely-1.5.0.dist-info/RECORD
